diarydek/__init__.py
diarydek/diarydek.py
diarydek/main.py
diarydek-0.0.25.dist-info/LICENSE
diarydek-0.0.25.dist-info/METADATA
diarydek-0.0.25.dist-info/WHEEL
diarydek-0.0.25.dist-info/entry_points.txt
diarydek-0.0.25.dist-info/top_level.txt
diarydek-0.0.25.dist-info/RECORD
