Metadata-Version: 2.1
Name: diarydek
Version: 0.0.25
Summary: A diary tool.
Author-email: Dan Kelley <kelley@dal.ca>
Project-URL: Homepage, https://github.com/dankelley/diarydek
Project-URL: Issues, https://github.com/dankelley/diarydek/issues
Classifier: Programming Language :: Python :: 3
Classifier: License :: OSI Approved :: MIT License
Classifier: Operating System :: OS Independent
Classifier: Development Status :: 3 - Alpha
Requires-Python: >=3.8
License-File: LICENSE
